yark/__init__.py
yark/__main__.py
yark/archiver/archive.py
yark/channel.py
yark/cli.py
yark/errors.py
yark/reporter.py
yark/templates/base.html
yark/templates/channel.html
yark/templates/index.html
yark/templates/video.html
yark/utils.py
yark/video.py
yark/viewer.py
yark-1.2.12.dist-info/LICENSE
yark-1.2.12.dist-info/WHEEL
yark-1.2.12.dist-info/entry_points.txt
yark-1.2.12.dist-info/METADATA
yark-1.2.12.dist-info/RECORD
