Metadata-Version: 2.1
Name: yark
Version: 1.2.12
Summary: YouTube archiving made simple.
Home-page: https://github.com/owez/yark
License: MIT
Author: Owen Griffiths
Author-email: root@ogriffiths.com
Requires-Python: >=3.9,<4.0
Classifier: License :: OSI Approved :: MIT License
Classifier: Programming Language :: Python :: 3
Classifier: Programming Language :: Python :: 3.9
Classifier: Programming Language :: Python :: 3.10
Classifier: Programming Language :: Python :: 3.11
Classifier: Topic :: Multimedia :: Video
Classifier: Topic :: System :: Archiving
Classifier: Topic :: System :: Archiving :: Backup
Requires-Dist: Flask (>=2.3.1,<3.0.0)
Requires-Dist: colorama (>=0.4.6,<0.5.0)
Requires-Dist: progress (>=1.6,<2.0)
Requires-Dist: requests (>=2.28.2,<3.0.0)
Requires-Dist: yt-dlp (==2024.10.07)
Project-URL: Repository, https://github.com/owez/yark
